avocado_robot/robot.py
avocado_robot/runner.py
avocado_framework_plugin_robot-113.0.dist-info/METADATA
avocado_framework_plugin_robot-113.0.dist-info/WHEEL
avocado_framework_plugin_robot-113.0.dist-info/entry_points.txt
avocado_framework_plugin_robot-113.0.dist-info/top_level.txt
avocado_framework_plugin_robot-113.0.dist-info/RECORD
