Metadata-Version: 2.4
Name: avocado-framework-plugin-robot
Version: 113.0
Summary: Avocado Plugin for Execution of Robot Framework tests
Home-page: http://avocado-framework.github.io/
Author: Avocado Developers
Author-email: avocado-devel@redhat.com
Requires-Dist: avocado-framework==113.0
Requires-Dist: robotframework<7.0,>=4.1; python_version >= "3.9"
Dynamic: author
Dynamic: author-email
Dynamic: description
Dynamic: description-content-type
Dynamic: home-page
Dynamic: requires-dist
Dynamic: summary
